[
  { "id": 3, "name": "Cheb", "slug": "cheb" },
  { "id": 6, "name": "Louny", "slug": "louny" },
  { "id": 9, "name": "Plzeň-město", "slug": "plzen-mesto" },
  { "id": 12, "name": "Strakonice", "slug": "strakonice" },
  { "id": 15, "name": "Pelhřimov", "slug": "pelhrimov" },
  { "id": 18, "name": "Příbram", "slug": "pribram" },
  { "id": 21, "name": "Praha 5", "slug": "praha-5" },
  { "id": 24, "name": "Praha 9", "slug": "praha-9" },
  { "id": 27, "name": "Praha 1", "slug": "praha-1" },
  { "id": 30, "name": "Kladno", "slug": "kladno" },
  { "id": 33, "name": "Děčín", "slug": "decin" },
  { "id": 36, "name": "Česká Lípa", "slug": "ceska-lipa" },
  { "id": 39, "name": "Trutnov", "slug": "trutnov" },
  { "id": 42, "name": "Kolín", "slug": "kolin" },
  { "id": 45, "name": "Hradec Králové", "slug": "hradec-kralove" },
  { "id": 48, "name": "Rychnov nad Kněžnou", "slug": "rychnov-nad-kneznou" },
  { "id": 51, "name": "Žďár nad Sázavou", "slug": "zdar-nad-sazavou" },
  { "id": 54, "name": "Znojmo", "slug": "znojmo" },
  { "id": 57, "name": "Vyškov", "slug": "vyskov" },
  { "id": 60, "name": "Brno-město", "slug": "brno-mesto" },
  { "id": 63, "name": "Přerov", "slug": "prerov" },
  { "id": 66, "name": "Olomouc", "slug": "olomouc" },
  { "id": 69, "name": "Frýdek-Místek", "slug": "frydek-mistek" },
  { "id": 72, "name": "Ostrava-město", "slug": "ostrava-mesto" },
  { "id": 75, "name": "Karviná", "slug": "karvina" },
  { "id": 78, "name": "Zlín", "slug": "zlin" },
  { "id": 81, "name": "Uherské Hradiště", "slug": "uherske-hradiste" }
]
